adbc_driver_netezza/__init__.py
adbc_driver_netezza/_static_version.py
adbc_driver_netezza/_version.py
adbc_driver_netezza/dbapi.py
adbc_driver_netezza/libadbc_driver_netezza.so
adbc_driver_netezza/libnzpq.so
adbc_driver_netezza-0.0.10.dist-info/METADATA
adbc_driver_netezza-0.0.10.dist-info/WHEEL
adbc_driver_netezza-0.0.10.dist-info/top_level.txt
adbc_driver_netezza-0.0.10.dist-info/RECORD
